Workbook

Sheet SOW
B2: Scope of Work / Renovation Budget
B3: Borrower: | E3: Entity Name LLC
B4: Primary Guarantor: | E4: First Last
B5: Subject Property Address: | E5: 123 Main St, Freehold, NJ 07728
B6: Date: | E6: =TODAY() -> 45160
B7: Contractor Name: | E7: - | L7: DRAW REQUEST
B8: Repair Line Item | D8: Description of Work | F8: Labor Cost | H8: Material Cost | J8: Total Cost | L8: % Complete | N8: Amount
B9: Demolition | F9: 0 | H9: 0 | J9: =F9+H9 -> 0 | N9: =J9*L9 -> 0
B10: Landscaping | F10: 0 | H10: 0 | J10: =F10+H10 -> 0 | N10: =J10*L10 -> 0
B11: Foundation/ Structural | F11: 0 | H11: 0 | J11: =F11+H11 -> 0 | N11: =J11*L11 -> 0
B12: Countertops | F12: 0 | H12: 0 | J12: =F12+H12 -> 0 | N12: =J12*L12 -> 0
B13: Cabinets | F13: 0 | H13: 0 | J13: =F13+H13 -> 0 | N13: =J13*L13 -> 0
B14: Appliances | F14: 0 | H14: 0 | J14: =F14+H14 -> 0 | N14: =J14*L14 -> 0
B15: Carpet | F15: 0 | H15: 0 | J15: =F15+H15 -> 0 | N15: =J15*L15 -> 0
B16: Hardwood | F16: 0 | H16: 0 | J16: =F16+H16 -> 0 | N16: =J16*L16 -> 0
B17: Tile | F17: 0 | H17: 0 | J17: =F17+H17 -> 0 | N17: =J17*L17 -> 0
B18: Siding | F18: 0 | H18: 0 | J18: =F18+H18 -> 0 | N18: =J18*L18 -> 0
B19: HVAC | F19: 0 | H19: 0 | J19: =F19+H19 -> 0 | N19: =J19*L19 -> 0
B20: Electrical | F20: 0 | H20: 0 | J20: =F20+H20 -> 0 | N20: =J20*L20 -> 0
... B51: - | F51: 0 | H51: 0 | J51: =F51+H51 -> 0 | N51: =J51*L51 -> 0
B52: Total: | D52: =SUM(D9:E51) -> 0 | F52: =SUM(F9:G51) -> 0 | H52: =SUM(H9:I51) -> 0 | J52: =F52+H52 -> 0 | L52: =(N52/J52) -> #DIV/0! | N52: =SUM(N9:O51) -> 0
B54: Escrow Holdback Policy on Property Rehabilitation
B56: Brrrr Funder LLC and/or its assigns (together, "BrrrrLoans") determines contingency and escrow holdback amouts on a case-by-case basis up to 100% of a construction budget. Property rehabilitation must begin within 60 days of closing And must be fully completed within a maximum of six months, subject to extreme weather. Rehabilitation draw proceeds will be disbursed by BrrrrLoans only upon completion of the work phases evidenced with subsequent inspections of the property. Draw proceeds will be disbursed based on the percentage of work completed compared to the total eligible budget.
B60: Suspension of Construction:
B61: Brrrr Funder LLC will track and, if applicable, take appropriate action if:
B62: (a) A construction/rehab draw request has not been submitted by the Borrower within 60 days of closing the loan,
B63: (b) A construction/rehab draw has not been submitted by the Borrower within 45 days of any previous construction/rehab draw,
B64: (c) If a loan has exceeded the construction draw period without having been extended,
B65: (d) Lender becomes aware of any unresolved pending liens or material inactivity at the site/project, or
B66: (e) Borrower is in default of the loan agreement and the cure period has expired.
B68: Fees:
B69: 3rd Party inspection/analysis of the Scope of Work varies between $295 and $595 depending on budget amount, property type, etc.
B70: $145 Draw Request Fee payable as follows: $115 Granite Inspection Fee + $30 Bank Wire Fee
... B75: Borrower Signature
B80: =_xlfn.CONCAT("By:"," ",E3) -> By: Entity Name LLC | F80: Date
B81: =_xlfn.CONCAT("c/o"," ",E4) -> c/o First Last

Sheet Draw Request 1
B2: Draw Request 1
B3: Borrower: | E3: =SOW!E3 -> Entity Name LLC
B4: Primary Guarantor: | E4: =SOW!E4 -> First Last
B5: Subject Property Address: | E5: =SOW!E5 -> 123 Main St, Freehold, NJ 07728
B6: Date:
B7: Contractor Name: | E7: =SOW!E7 -> - | F7: Labor Cost | H7: Material Cost | J7: Total Cost | L7: % Complete | N7: Amount
B8: Repair Line Item | D8: Description of Work | F8: Labor Cost | H8: Material Cost | J8: Total Cost | L8: % Complete | N8: Amount
B9: =SOW!B9 -> Demolition
B10: =SOW!B10 -> Landscaping | F10: 0 | H10: 0 | J10: =F10+H10 -> 0 | N10: =J10*L10 -> 0
B11: =SOW!B11 -> Foundation/ Structural | F11: 0 | H11: 0 | J11: =F11+H11 -> 0 | N11: =J11*L11 -> 0
B12: =SOW!B12 -> Countertops | F12: 0 | H12: 0 | J12: =F12+H12 -> 0 | N12: =J12*L12 -> 0
B13: =SOW!B13 -> Cabinets | F13: 0 | H13: 0 | J13: =F13+H13 -> 0 | N13: =J13*L13 -> 0
B14: =SOW!B14 -> Appliances | F14: 0 | H14: 0 | J14: =F14+H14 -> 0 | N14: =J14*L14 -> 0
B15: =SOW!B15 -> Carpet | F15: 0 | H15: 0 | J15: =F15+H15 -> 0 | N15: =J15*L15 -> 0
B16: =SOW!B16 -> Hardwood | F16: 0 | H16: 0 | J16: =F16+H16 -> 0 | N16: =J16*L16 -> 0
B17: =SOW!B17 -> Tile | F17: 0 | H17: 0 | J17: =F17+H17 -> 0 | N17: =J17*L17 -> 0
B18: =SOW!B18 -> Siding | F18: 0 | H18: 0 | J18: =F18+H18 -> 0 | N18: =J18*L18 -> 0
B19: =SOW!B19 -> HVAC | F19: 0 | H19: 0 | J19: =F19+H19 -> 0 | N19: =J19*L19 -> 0
B20: =SOW!B20 -> Electrical | F20: 0 | H20: 0 | J20: =F20+H20 -> 0 | N20: =J20*L20 -> 0
B21: =SOW!B21 -> Plumbing | F21: 0 | H21: 0 | J21: =F21+H21 -> 0 | N21: =J21*L21 -> 0
... B51: =SOW!B51 -> - | F51: 0 | H51: 0 | J51: =F51+H51 -> 0 | N51: =J51*L51 -> 0
B52: Total: | F52: =SUM(F8:G51) -> 0 | H52: =SUM(H8:I51) -> 0 | J52: =F52+H52 -> 0 | L52: =(N52/J52) -> #DIV/0! | N52: =SUM(N8:O51) -> 0
B54: Escrow Holdback Policy on Property Rehabilitation
B56: Brrrr Funder LLC and/or its assigns (together, "BrrrrLoans") determines contingency and escrow holdback amouts on a case-by-case basis up to 100% of a construction budget. Property rehabilitation must begin within 60 days of closing And must be fully completed within a maximum of six months, subject to extreme weather. Rehabilitation draw proceeds will be disbursed by BrrrrLoans only upon completion of the work phases evidenced with subsequent inspections of the property. Draw proceeds will be disbursed based on the percentage of work completed compared to the total eligible budget.
B60: Suspension of Construction:
B61: Brrrr Funder LLC will track and, if applicable, take appropriate action if:
B62: (a) A construction/rehab draw request has not been submitted by the Borrower within 60 days of closing the loan,
B63: (b) A construction/rehab draw has not been submitted by the Borrower within 45 days of any previous construction/rehab draw,
B64: (c) If a loan has exceeded the construction draw period without having been extended,
B65: (d) Lender becomes aware of any unresolved pending liens or material inactivity at the site/project, or
B66: (e) Borrower is in default of the loan agreement and the cure period has expired.
B68: Fees:
B69: 3rd Party inspection/analysis of the Scope of Work varies between $295 and $595 depending on budget amount, property type, etc.
B70: $145 Draw Request Fee payable as follows: $115 Granite Inspection Fee + $30 Bank Wire Fee
... B75: Borrower Signature
B80: =_xlfn.CONCAT("By:"," ",E2) -> By: | F80: Date
B81: =_xlfn.CONCAT("c/o"," ",E3) -> c/o Entity Name LLC

Sheet Draw Request 2
B2: Draw Request 2
B3: Borrower: | E3: =SOW!E3 -> Entity Name LLC
B4: Primary Guarantor: | E4: =SOW!E4 -> First Last
B5: Subject Property Address: | E5: =SOW!E5 -> 123 Main St, Freehold, NJ 07728
B6: Date:
B7: Contractor Name: | E7: =SOW!E7 -> - | F7: Labor Cost | H7: Material Cost | J7: Total Cost | L7: % Complete | N7: Amount
B8: Repair Line Item | D8: Description of Work | F8: Labor Cost | H8: Material Cost | J8: Total Cost | L8: % Complete | N8: Amount
B9: =SOW!B9 -> Demolition
B10: =SOW!B10 -> Landscaping | F10: 0 | H10: 0 | J10: =F10+H10 -> 0 | N10: =J10*L10 -> 0
B11: =SOW!B11 -> Foundation/ Structural | F11: 0 | H11: 0 | J11: =F11+H11 -> 0 | N11: =J11*L11 -> 0
B12: =SOW!B12 -> Countertops | F12: 0 | H12: 0 | J12: =F12+H12 -> 0 | N12: =J12*L12 -> 0
B13: =SOW!B13 -> Cabinets | F13: 0 | H13: 0 | J13: =F13+H13 -> 0 | N13: =J13*L13 -> 0
B14: =SOW!B14 -> Appliances | F14: 0 | H14: 0 | J14: =F14+H14 -> 0 | N14: =J14*L14 -> 0
B15: =SOW!B15 -> Carpet | F15: 0 | H15: 0 | J15: =F15+H15 -> 0 | N15: =J15*L15 -> 0
B16: =SOW!B16 -> Hardwood | F16: 0 | H16: 0 | J16: =F16+H16 -> 0 | N16: =J16*L16 -> 0
B17: =SOW!B17 -> Tile | F17: 0 | H17: 0 | J17: =F17+H17 -> 0 | N17: =J17*L17 -> 0
B18: =SOW!B18 -> Siding | F18: 0 | H18: 0 | J18: =F18+H18 -> 0 | N18: =J18*L18 -> 0
B19: =SOW!B19 -> HVAC | F19: 0 | H19: 0 | J19: =F19+H19 -> 0 | N19: =J19*L19 -> 0
B20: =SOW!B20 -> Electrical | F20: 0 | H20: 0 | J20: =F20+H20 -> 0 | N20: =J20*L20 -> 0
B21: =SOW!B21 -> Plumbing | F21: 0 | H21: 0 | J21: =F21+H21 -> 0 | N21: =J21*L21 -> 0
... B51: =SOW!B51 -> - | F51: 0 | H51: 0 | J51: =F51+H51 -> 0 | N51: =J51*L51 -> 0
B52: Total: | F52: =SUM(F8:G51) -> 0 | H52: =SUM(H8:I51) -> 0 | J52: =F52+H52 -> 0 | L52: =(N52/J52) -> #DIV/0! | N52: =SUM(N8:O51) -> 0
B54: Escrow Holdback Policy on Property Rehabilitation
B56: Brrrr Funder LLC and/or its assigns (together, "BrrrrLoans") determines contingency and escrow holdback amouts on a case-by-case basis up to 100% of a construction budget. Property rehabilitation must begin within 60 days of closing And must be fully completed within a maximum of six months, subject to extreme weather. Rehabilitation draw proceeds will be disbursed by BrrrrLoans only upon completion of the work phases evidenced with subsequent inspections of the property. Draw proceeds will be disbursed based on the percentage of work completed compared to the total eligible budget.
B60: Suspension of Construction:
B61: Brrrr Funder LLC will track and, if applicable, take appropriate action if:
B62: (a) A construction/rehab draw request has not been submitted by the Borrower within 60 days of closing the loan,
B63: (b) A construction/rehab draw has not been submitted by the Borrower within 45 days of any previous construction/rehab draw,
B64: (c) If a loan has exceeded the construction draw period without having been extended,
B65: (d) Lender becomes aware of any unresolved pending liens or material inactivity at the site/project, or
B66: (e) Borrower is in default of the loan agreement and the cure period has expired.
B68: Fees:
B69: 3rd Party inspection/analysis of the Scope of Work varies between $295 and $595 depending on budget amount, property type, etc.
B70: $145 Draw Request Fee payable as follows: $115 Granite Inspection Fee + $30 Bank Wire Fee
... B75: Borrower Signature
B80: =_xlfn.CONCAT("By:"," ",E2) -> By: | F80: Date
B81: =_xlfn.CONCAT("c/o"," ",E3) -> c/o Entity Name LLC

Sheet Draw Request 3
B2: Draw Request 3
B3: Borrower: | E3: =SOW!E3 -> Entity Name LLC
B4: Primary Guarantor: | E4: =SOW!E4 -> First Last
B5: Subject Property Address: | E5: =SOW!E5 -> 123 Main St, Freehold, NJ 07728
B6: Date:
B7: Contractor Name: | E7: =SOW!E7 -> - | F7: Labor Cost | H7: Material Cost | J7: Total Cost | L7: % Complete | N7: Amount
B8: Repair Line Item | D8: Description of Work | F8: Labor Cost | H8: Material Cost | J8: Total Cost | L8: % Complete | N8: Amount
B9: =SOW!B9 -> Demolition
B10: =SOW!B10 -> Landscaping | F10: 0 | H10: 0 | J10: =F10+H10 -> 0 | N10: =J10*L10 -> 0
B11: =SOW!B11 -> Foundation/ Structural | F11: 0 | H11: 0 | J11: =F11+H11 -> 0 | N11: =J11*L11 -> 0
B12: =SOW!B12 -> Countertops | F12: 0 | H12: 0 | J12: =F12+H12 -> 0 | N12: =J12*L12 -> 0
B13: =SOW!B13 -> Cabinets | F13: 0 | H13: 0 | J13: =F13+H13 -> 0 | N13: =J13*L13 -> 0
B14: =SOW!B14 -> Appliances | F14: 0 | H14: 0 | J14: =F14+H14 -> 0 | N14: =J14*L14 -> 0
B15: =SOW!B15 -> Carpet | F15: 0 | H15: 0 | J15: =F15+H15 -> 0 | N15: =J15*L15 -> 0
B16: =SOW!B16 -> Hardwood | F16: 0 | H16: 0 | J16: =F16+H16 -> 0 | N16: =J16*L16 -> 0
B17: =SOW!B17 -> Tile | F17: 0 | H17: 0 | J17: =F17+H17 -> 0 | N17: =J17*L17 -> 0
B18: =SOW!B18 -> Siding | F18: 0 | H18: 0 | J18: =F18+H18 -> 0 | N18: =J18*L18 -> 0
B19: =SOW!B19 -> HVAC | F19: 0 | H19: 0 | J19: =F19+H19 -> 0 | N19: =J19*L19 -> 0
B20: =SOW!B20 -> Electrical | F20: 0 | H20: 0 | J20: =F20+H20 -> 0 | N20: =J20*L20 -> 0
B21: =SOW!B21 -> Plumbing | F21: 0 | H21: 0 | J21: =F21+H21 -> 0 | N21: =J21*L21 -> 0
... B51: =SOW!B51 -> - | F51: 0 | H51: 0 | J51: =F51+H51 -> 0 | N51: =J51*L51 -> 0
B52: Total: | F52: =SUM(F8:G51) -> 0 | H52: =SUM(H8:I51) -> 0 | J52: =F52+H52 -> 0 | L52: =(N52/J52) -> #DIV/0! | N52: =SUM(N8:O51) -> 0
B54: Escrow Holdback Policy on Property Rehabilitation
B56: Brrrr Funder LLC and/or its assigns (together, "BrrrrLoans") determines contingency and escrow holdback amouts on a case-by-case basis up to 100% of a construction budget. Property rehabilitation must begin within 60 days of closing And must be fully completed within a maximum of six months, subject to extreme weather. Rehabilitation draw proceeds will be disbursed by BrrrrLoans only upon completion of the work phases evidenced with subsequent inspections of the property. Draw proceeds will be disbursed based on the percentage of work completed compared to the total eligible budget.
B60: Suspension of Construction:
B61: Brrrr Funder LLC will track and, if applicable, take appropriate action if:
B62: (a) A construction/rehab draw request has not been submitted by the Borrower within 60 days of closing the loan,
B63: (b) A construction/rehab draw has not been submitted by the Borrower within 45 days of any previous construction/rehab draw,
B64: (c) If a loan has exceeded the construction draw period without having been extended,
B65: (d) Lender becomes aware of any unresolved pending liens or material inactivity at the site/project, or
B66: (e) Borrower is in default of the loan agreement and the cure period has expired.
B68: Fees:
B69: 3rd Party inspection/analysis of the Scope of Work varies between $295 and $595 depending on budget amount, property type, etc.
B70: $145 Draw Request Fee payable as follows: $115 Granite Inspection Fee + $30 Bank Wire Fee
... B75: Borrower Signature
B80: =_xlfn.CONCAT("By:"," ",E2) -> By: | F80: Date
B81: =_xlfn.CONCAT("c/o"," ",E3) -> c/o Entity Name LLC

Sheet Draw Request 4
B2: Draw Request 4
B3: Borrower: | E3: =SOW!E3 -> Entity Name LLC
B4: Primary Guarantor: | E4: =SOW!E4 -> First Last
B5: Subject Property Address: | E5: =SOW!E5 -> 123 Main St, Freehold, NJ 07728
B6: Date:
B7: Contractor Name: | E7: =SOW!E7 -> - | F7: Labor Cost | H7: Material Cost | J7: Total Cost | L7: % Complete | N7: Amount
B8: Repair Line Item | D8: Description of Work | F8: Labor Cost | H8: Material Cost | J8: Total Cost | L8: % Complete | N8: Amount
B9: =SOW!B9 -> Demolition
B10: =SOW!B10 -> Landscaping | F10: 0 | H10: 0 | J10: =F10+H10 -> 0 | N10: =J10*L10 -> 0
B11: =SOW!B11 -> Foundation/ Structural | F11: 0 | H11: 0 | J11: =F11+H11 -> 0 | N11: =J11*L11 -> 0
B12: =SOW!B12 -> Countertops | F12: 0 | H12: 0 | J12: =F12+H12 -> 0 | N12: =J12*L12 -> 0
B13: =SOW!B13 -> Cabinets | F13: 0 | H13: 0 | J13: =F13+H13 -> 0 | N13: =J13*L13 -> 0
B14: =SOW!B14 -> Appliances | F14: 0 | H14: 0 | J14: =F14+H14 -> 0 | N14: =J14*L14 -> 0
B15: =SOW!B15 -> Carpet | F15: 0 | H15: 0 | J15: =F15+H15 -> 0 | N15: =J15*L15 -> 0
B16: =SOW!B16 -> Hardwood | F16: 0 | H16: 0 | J16: =F16+H16 -> 0 | N16: =J16*L16 -> 0
B17: =SOW!B17 -> Tile | F17: 0 | H17: 0 | J17: =F17+H17 -> 0 | N17: =J17*L17 -> 0
B18: =SOW!B18 -> Siding | F18: 0 | H18: 0 | J18: =F18+H18 -> 0 | N18: =J18*L18 -> 0
B19: =SOW!B19 -> HVAC | F19: 0 | H19: 0 | J19: =F19+H19 -> 0 | N19: =J19*L19 -> 0
B20: =SOW!B20 -> Electrical | F20: 0 | H20: 0 | J20: =F20+H20 -> 0 | N20: =J20*L20 -> 0
B21: =SOW!B21 -> Plumbing | F21: 0 | H21: 0 | J21: =F21+H21 -> 0 | N21: =J21*L21 -> 0
... B51: =SOW!B51 -> - | F51: 0 | H51: 0 | J51: =F51+H51 -> 0 | N51: =J51*L51 -> 0
B52: Total: | F52: =SUM(F8:G51) -> 0 | H52: =SUM(H8:I51) -> 0 | J52: =F52+H52 -> 0 | L52: =(N52/J52) -> #DIV/0! | N52: =SUM(N8:O51) -> 0
B54: Escrow Holdback Policy on Property Rehabilitation
B56: Brrrr Funder LLC and/or its assigns (together, "BrrrrLoans") determines contingency and escrow holdback amouts on a case-by-case basis up to 100% of a construction budget. Property rehabilitation must begin within 60 days of closing And must be fully completed within a maximum of six months, subject to extreme weather. Rehabilitation draw proceeds will be disbursed by BrrrrLoans only upon completion of the work phases evidenced with subsequent inspections of the property. Draw proceeds will be disbursed based on the percentage of work completed compared to the total eligible budget.
B60: Suspension of Construction:
B61: Brrrr Funder LLC will track and, if applicable, take appropriate action if:
B62: (a) A construction/rehab draw request has not been submitted by the Borrower within 60 days of closing the loan,
B63: (b) A construction/rehab draw has not been submitted by the Borrower within 45 days of any previous construction/rehab draw,
B64: (c) If a loan has exceeded the construction draw period without having been extended,
B65: (d) Lender becomes aware of any unresolved pending liens or material inactivity at the site/project, or
B66: (e) Borrower is in default of the loan agreement and the cure period has expired.
B68: Fees:
B69: 3rd Party inspection/analysis of the Scope of Work varies between $295 and $595 depending on budget amount, property type, etc.
B70: $145 Draw Request Fee payable as follows: $115 Granite Inspection Fee + $30 Bank Wire Fee
... B75: Borrower Signature
B80: =_xlfn.CONCAT("By:"," ",E2) -> By: | F80: Date
B81: =_xlfn.CONCAT("c/o"," ",E3) -> c/o Entity Name LLC
